bceiam/__init__.py
bceiam/bce_base_client.py
bceiam/bce_client_configuration.py
bceiam/bce_response.py
bceiam/compat.py
bceiam/exception.py
bceiam/handler.py
bceiam/protocol.py
bceiam/region.py
bceiam/utils.py
bceiam/auth/__init__.py
bceiam/auth/bce_credentials.py
bceiam/auth/bce_v1_signer.py
bceiam/auth/iam_credentials.py
bceiam/auth/idaas_credentials.py
bceiam/cache/__init__.py
bceiam/cache/token_cache.py
bceiam/http/__init__.py
bceiam/http/bce_http_client.py
bceiam/http/handler.py
bceiam/http/http_content_types.py
bceiam/http/http_headers.py
bceiam/http/http_methods.py
bceiam/middleware/__init__.py
bceiam/middleware/auth/__init__.py
bceiam/middleware/auth/const.py
bceiam/middleware/auth/iam_session.py
bceiam/middleware/auth/idaas_session.py
bceiam/middleware/auth/utils.py
bceiam/retry/__init__.py
bceiam/retry/retry_policy.py
bceiam/services/__init__.py
bceiam/services/iam/__init__.py
bceiam/services/iam/iam_client.py
bceiam/services/idaas/__init__.py
bceiam/services/idaas/idaas_client.py
bceiam/services/sts/__init__.py
bceiam/services/sts/sts_client.py
bceiam-0.0.2.dist-info/METADATA
bceiam-0.0.2.dist-info/WHEEL
bceiam-0.0.2.dist-info/top_level.txt
bceiam-0.0.2.dist-info/RECORD
