Metadata-Version: 2.1
Name: bceiam
Version: 0.0.2
Summary: project descriptions here
Home-page: http://icode.baidu.com/repos/baidu/bce-idaas/sdk-python/tree/master
Author: zhoubohan
Author-email: zhoubohan@baidu.com
License: MIT
Classifier: Programming Language :: Python
Classifier: Programming Language :: Python :: 2
Classifier: Programming Language :: Python :: 2.7
Classifier: Programming Language :: Python :: 3.8
Requires-Python: >=2.7, !=3.0.*, !=3.1.*, !=3.2.*, <4
Requires-Dist: pycryptodome>=3.8.0
Requires-Dist: future>=0.6.0
Requires-Dist: six>=1.4.0
Requires-Dist: bceserver
Requires-Dist: bcelogger
Requires-Dist: fastapi
